{
  "project_info": {
    "project_number": "450320988569",
    "firebase_url": "https://matching-5e6da.firebaseio.com",
    "project_id": "matching-5e6da",
    "storage_bucket": "matching-5e6da.appspot.com"
  },
  "client": [
    {
      "client_info": {
        "mobilesdk_app_id": "1:450320988569:android:344c8130258a0f28747b08",
        "android_client_info": {
          "package_name": "com.example.matchthetiles"
        }
      },
      "oauth_client": [
        {
          "client_id": "450320988569-04mo1d302f1kn335bfo6tl33arots78b.apps.googleusercontent.com",
          "client_type": 1,
          "android_info": {
            "package_name": "com.example.matchthetiles",
            "certificate_hash": "65930d8498aaf6158855f99ee790751ec00e8c04"
          }
        },
        {
          "client_id": "450320988569-don69cfnj7indt2r69j9fiaksvajul1u.apps.googleusercontent.com",
          "client_type": 3
        }
      ],
      "api_key": [
        {
          "current_key": "AIzaSyD6fbRkVDUWENu6obEMH3g2HPfN4UwD7Bw"
        }
      ],
      "services": {
        "appinvite_service": {
          "other_platform_oauth_client": [
            {
              "client_id": "450320988569-don69cfnj7indt2r69j9fiaksvajul1u.apps.googleusercontent.com",
              "client_type": 3
            }
          ]
        }
      }
    }
  ],
  "configuration_version": "1"
}